Metadata-Version: 1.1
Name: pypi-uploader
Version: 1.0.0
Summary: Upload source distributions to your PyPI server.
Home-page: https://github.com/ignacysokolowski/pypi-uploader
Author: Ignacy Sokolowski
Author-email: ignacy.sokolowski@gmail.com
License: Copyright (c) 2014 Ignacy Sokołowski
